NNVisualiser.py
__init__.py
NNVisualiser-1.0.0.dist-info/LICENSE.txt
NNVisualiser-1.0.0.dist-info/METADATA
NNVisualiser-1.0.0.dist-info/WHEEL
NNVisualiser-1.0.0.dist-info/top_level.txt
NNVisualiser-1.0.0.dist-info/RECORD
