Metadata-Version: 2.1
Name: NNVisualiser
Version: 1.0.0
Summary: A Neural Network Visualiser as a Python package utilizing Matplotlib, visualizes plot coordinates from NeuralNetworkCoordinates for single-input, single-output neural networks. Aligned with Explainable AI, it offers concise insights, catering to researchers focused on understanding specific network architectures.
Author-email: Caxton Emerald S <ces.softwaresolutions@gmail.com>, Vengattaraman T <vengattaraman.t@pondiuni.ac.in>
Maintainer-email: Caxton Emerald S <ces.softwaresolutions@gmail.com>
License: The Cat Standard License v1.0
Project-URL: Homepage, https://caxtonemerald-s.github.io/NNVisualiser/
Project-URL: Bug Reports, https://github.com/CaxtonEmerald-S/NNVisualiser/issues
Project-URL: Source, https://github.com/CaxtonEmerald-S/NNVisualiser/
Project-URL: Documentation, https://github.com/CaxtonEmerald-S/NNVisualiser/wiki
Project-URL: Wiki, https://github.com/CaxtonEmerald-S/NNVisualiser/wiki
Keywords: neural networks,ANN,analysis,coordinates,visualiser,visualise,regression,classification,functional transformation
Classifier: Development Status :: 4 - Beta
Classifier: Intended Audience :: Developers
Classifier: Intended Audience :: Education
Classifier: Intended Audience :: Science/Research
Classifier: Intended Audience :: Information Technology
Classifier: Topic :: Software Development :: Build Tools
Classifier: Topic :: Software Development :: Libraries :: Python Modules
Classifier: Topic :: Scientific/Engineering :: Artificial Intelligence
Classifier: Topic :: Scientific/Engineering :: Visualization
Classifier: Topic :: Scientific/Engineering
Classifier: License :: Other/Proprietary License
Classifier: Programming Language :: Python :: 3.10
Classifier: Programming Language :: Python :: 3 :: Only
Requires-Python: >=3.10.12
License-File: LICENSE.txt
Requires-Dist: numpy >=1.23.5
Requires-Dist: keras >=2.14.0
Requires-Dist: matplotlib >=3.7.1
Requires-Dist: tensorflow >=2.14.0
Requires-Dist: NeuralNetworkCoordinates >=1.0.0
